{
  "name": "A Remixed Digital Echasketch  Again 2 martin - no religion  + disco Fruits Machine + Raron + mstress + Rovastar (AdamFX Remix)4",
  "init_code": "mv_x\nmv_y\nmonitor",
  "per_frame": "zoom\n\ncx\ncy\n\n\n\nob_r\nob_b\nob_g\n\nib_r\nib_b\nib_g\n\n\nrot\n\n\n\ndecay\n\n\nwec\nweconz\nwecrut\ntri\n\n\nt1\nt3\nt6\nt7\n\n\nq1\nq2\nq6",
  "per_pixel": "bamx\nboom\nbom\n\n\nspeed\nspeedA\nspeedB\nspeedC\n\nshox\nrhox\nrox\n\ndaz\n\n\n\n\nwec\nweconz\nwecrut\ntri\n\n\n\nwarp\n\nq3\nq8\nq5\nq6\nq4\n\n\nwec\nweconz\nwecrut\ntri\n\n\n\nt1\nt3\nt6\nt7",
  "shapes": [
    {
      "enabled": 1,
      "sides": 4,
      "additive": 0,
      "thickOutline": 0,
      "textured": 0,
      "code": "",
      "baseVals": {
        "x": 0.5,
        "y": 0.5,
        "ang": 0,
        "size": 0.04896,
        "r": 0.5,
        "g": 1,
        "b": 0.9,
        "a": 1,
        "r2": 0.83,
        "g2": 0.93,
        "b2": 0.8,
        "a2": 1,
        "border_r": 1,
        "border_g": 1,
        "border_b": 0,
        "border_a": 0,
        "tex_ang": 1.00531,
        "tex_zoom": 1.53117
      }
    },
    {
      "enabled": 0,
      "sides": 4,
      "additive": 0,
      "thickOutline": 1,
      "textured": 0,
      "code": "",
      "baseVals": {
        "x": 0.4,
        "y": 0.5,
        "ang": 0,
        "size": 2.36696,
        "r": 0.5,
        "g": 0,
        "b": 1,
        "a": 0.2,
        "r2": 0.7,
        "g2": 0.4,
        "b2": 0,
        "a2": 0,
        "border_r": 0.5,
        "border_g": 0.5,
        "border_b": 0.5,
        "border_a": 0,
        "tex_ang": 3.45575,
        "tex_zoom": 0.99305
      }
    },
    {
      "enabled": 1,
      "sides": 4,
      "additive": 0,
      "thickOutline": 0,
      "textured": 0,
      "code": "",
      "baseVals": {
        "x": 0.503,
        "y": 0.5,
        "ang": 0,
        "size": 0.03886,
        "r": 1,
        "g": 0.1,
        "b": 0,
        "a": 0.9,
        "r2": 1,
        "g2": 1,
        "b2": 1,
        "a2": 0,
        "border_r": 0.5,
        "border_g": 0.5,
        "border_b": 0.5,
        "border_a": 0,
        "tex_ang": 0,
        "tex_zoom": 0.60986
      }
    },
    {
      "enabled": 0,
      "sides": 63,
      "additive": 0,
      "thickOutline": 0,
      "textured": 1,
      "code": "",
      "baseVals": {
        "x": 0.5,
        "y": 1,
        "ang": 0,
        "size": 0.54822,
        "r": 1,
        "g": 1,
        "b": 1,
        "a": 1,
        "r2": 1,
        "g2": 1,
        "b2": 1,
        "a2": 0,
        "border_r": 0.5,
        "border_g": 0.5,
        "border_b": 0.5,
        "border_a": 0,
        "tex_ang": 0,
        "tex_zoom": 0.49981
      }
    }
  ],
  "waves": [
    {
      "enabled": 1,
      "samples": 512,
      "spectrum": 0,
      "dots": 0,
      "thick": 0,
      "additive": 1,
      "r": 1,
      "g": 1,
      "b": 1,
      "a": 0.6,
      "scaling": 0.89152,
      "smoothing": 0.82,
      "sep": 120,
      "code_per_frame": "t2",
      "code_per_point": "k1\nk2\nxi\nyi\n\ndx\ndy\n\nx\ny\n\na\na"
    },
    {
      "enabled": 0,
      "samples": 512,
      "spectrum": 0,
      "dots": 1,
      "thick": 1,
      "additive": 0,
      "r": 1,
      "g": 1,
      "b": 1,
      "a": 0.1,
      "scaling": 0.89152,
      "smoothing": 0.82,
      "sep": 0,
      "code_per_frame": "tm\nt1\nt2\nt3\n\ntic\ntin\n\ntva\ntvb\ntvc\n\nq1\nq2\nq3\n\nsz\nlen\nt4",
      "code_per_point": "xi\nyi\n\nx\n\na"
    },
    {
      "enabled": 0,
      "samples": 512,
      "spectrum": 0,
      "dots": 0,
      "thick": 1,
      "additive": 0,
      "r": 0,
      "g": 0.2,
      "b": 0,
      "a": 1,
      "scaling": 0.89152,
      "smoothing": 0.82,
      "sep": 0,
      "code_per_frame": "tm\nt1\nt2\nt3\n\ntic\ntin\n\ntva\ntvb\ntvc\n\nq1\nq2\nq3\n\nsz\nlen\nt4",
      "code_per_point": ""
    },
    {
      "enabled": 0,
      "samples": 512,
      "spectrum": 1,
      "dots": 1,
      "thick": 0,
      "additive": 0,
      "r": 1,
      "g": 1,
      "b": 1,
      "a": 1,
      "scaling": 1,
      "smoothing": 0.5,
      "sep": 0,
      "code_per_frame": "",
      "code_per_point": ""
    }
  ],
  "zoom": 0.99951,
  "rot": 0,
  "cx": 0.5,
  "cy": 0.5,
  "warp": 0.00564,
  "gamma": 1.98,
  "warp_speed": 1,
  "wave_scale": 10.437,
  "decay": 0.5
}