{
  "name": "gaping h - stop me from observing nz",
  "init_code": "x1\ny1\n\nx2\ny2\n\nx3\ny3\n\nvr1\nvr2\nvr3\n\nvx1\nvx2\nvx3",
  "per_frame": "zoom\nwarp\nwave_a\n\nr\nmonitor\nvr\nbounce\nvx1\nbounce\nvy1\nbounce\nvy1\n\nvr\nbounce\nvx2\nbounce\nvy2\nbounce\nvy2\n\nvr\nbounce\nvx3\nbounce\nvy3\nbounce\nvy3\n\nbounce\nbounce\nref_ang\nv1\nvr\nvx1\n+ sin(ref_ang+asin(1))*v2*cos(w2-ref_ang-asin(1)), vx1);\nvy1\n+ cos(ref_ang+asin(1))*v2*cos(w2-ref_ang-asin(1)), vy1);\nvx2\n+ sin(ref_ang+asin(1))*v1*cos(w1-ref_ang-asin(1)), vx2);\nvy2\n+ cos(ref_ang+asin(1))*v1*cos(w1-ref_ang-asin(1)), vy2);\nvr\nv2r\n\nbounce\nbounce\nref_ang\nv1\nvr\nvx1\n+ sin(ref_ang+asin(1))*v2*cos(w2-ref_ang-asin(1)), vx1);\nvy1\n+ cos(ref_ang+asin(1))*v2*cos(w2-ref_ang-asin(1)), vy1);\nvx3\n+ sin(ref_ang+asin(1))*v1*cos(w1-ref_ang-asin(1)), vx3);\nvy3\n+ cos(ref_ang+asin(1))*v1*cos(w1-ref_ang-asin(1)), vy3);\nvr\nv2r\n\nbounce\nbounce\nref_ang\nv1\nvr\nvx3\n+ sin(ref_ang+asin(1))*v2*cos(w2-ref_ang-asin(1)), vx3);\nvy3\n+ cos(ref_ang+asin(1))*v2*cos(w2-ref_ang-asin(1)), vy3);\nvx2\n+ sin(ref_ang+asin(1))*v1*cos(w1-ref_ang-asin(1)), vx2);\nvy2\n+ cos(ref_ang+asin(1))*v1*cos(w1-ref_ang-asin(1)), vy2);\nvr\nv2r\n\n\n\n\nq1\nq2\nq3\n\nq4\nq7\nq10\n\nq13\nq14",
  "per_pixel": "du\ndv\ndist\nang2\nmult\ndx\ndy",
  "shapes": [
    {
      "enabled": 1,
      "sides": 14,
      "additive": 0,
      "thickOutline": 0,
      "textured": 0,
      "code": "",
      "baseVals": {
        "x": 0.5,
        "y": 0.5,
        "ang": 0,
        "size": 0.1026,
        "r": 1,
        "g": 0,
        "b": 0,
        "a": 1,
        "r2": 1,
        "g2": 0,
        "b2": 0,
        "a2": 1,
        "border_r": 1,
        "border_g": 1,
        "border_b": 1,
        "border_a": 0,
        "tex_ang": 0.62832,
        "tex_zoom": 1
      }
    },
    {
      "enabled": 1,
      "sides": 23,
      "additive": 0,
      "thickOutline": 0,
      "textured": 0,
      "code": "",
      "baseVals": {
        "x": 0.5,
        "y": 0.5,
        "ang": 0.43982,
        "size": 0.10262,
        "r": 1,
        "g": 0,
        "b": 0,
        "a": 0.5,
        "r2": 1,
        "g2": 0,
        "b2": 0,
        "a2": 0.5,
        "border_r": 1,
        "border_g": 1,
        "border_b": 1,
        "border_a": 0,
        "tex_ang": 0.62832,
        "tex_zoom": 1
      }
    },
    {
      "enabled": 0,
      "sides": 14,
      "additive": 1,
      "thickOutline": 0,
      "textured": 0,
      "code": "",
      "baseVals": {
        "x": 0.5,
        "y": 0.5,
        "ang": 0,
        "size": 0.20269,
        "r": 1,
        "g": 0,
        "b": 0,
        "a": 1,
        "r2": 1,
        "g2": 0,
        "b2": 0,
        "a2": 1,
        "border_r": 1,
        "border_g": 1,
        "border_b": 1,
        "border_a": 0,
        "tex_ang": 0.62832,
        "tex_zoom": 1
      }
    },
    {
      "enabled": 0,
      "sides": 14,
      "additive": 1,
      "thickOutline": 0,
      "textured": 0,
      "code": "",
      "baseVals": {
        "x": 0.5,
        "y": 0.5,
        "ang": 0,
        "size": 0.22389,
        "r": 1,
        "g": 0,
        "b": 0,
        "a": 1,
        "r2": 1,
        "g2": 0,
        "b2": 0,
        "a2": 1,
        "border_r": 1,
        "border_g": 1,
        "border_b": 1,
        "border_a": 0,
        "tex_ang": 0.62832,
        "tex_zoom": 1
      }
    }
  ],
  "waves": [
    {
      "enabled": 0,
      "samples": 512,
      "spectrum": 0,
      "dots": 0,
      "thick": 1,
      "additive": 0,
      "r": 1,
      "g": 1,
      "b": 1,
      "a": 1,
      "scaling": 1,
      "smoothing": 0.5,
      "sep": 0,
      "code_per_frame": "",
      "code_per_point": "ma\nma\n\nmx\nmy\n\nmx\nmy\nmx\nmy\n\nx\ny\n\na"
    },
    {
      "enabled": 0,
      "samples": 512,
      "spectrum": 0,
      "dots": 0,
      "thick": 1,
      "additive": 0,
      "r": 1,
      "g": 1,
      "b": 1,
      "a": 1,
      "scaling": 1,
      "smoothing": 0.5,
      "sep": 0,
      "code_per_frame": "",
      "code_per_point": "ma\nma\n\nmx\nmy\n\nmx\nmy\nmx\nmy\n\nx\ny\n\na"
    },
    {
      "enabled": 0,
      "samples": 512,
      "spectrum": 0,
      "dots": 0,
      "thick": 1,
      "additive": 0,
      "r": 1,
      "g": 1,
      "b": 1,
      "a": 1,
      "scaling": 1,
      "smoothing": 0.5,
      "sep": 0,
      "code_per_frame": "",
      "code_per_point": "ma\nma\n\nmx\nmy\n\nmx\nmy\nmx\nmy\n\nx\ny\n\na"
    },
    {
      "enabled": 0,
      "samples": 512,
      "spectrum": 0,
      "dots": 0,
      "thick": 1,
      "additive": 0,
      "r": 1,
      "g": 1,
      "b": 1,
      "a": 1,
      "scaling": 1,
      "smoothing": 0.5,
      "sep": 0,
      "code_per_frame": "",
      "code_per_point": "ma\nma\n\nmx\nmy\n\nmx\nmy\nmx\nmy\n\nx\ny\n\na"
    }
  ],
  "zoom": 0.99951,
  "rot": 0,
  "cx": 0.5,
  "cy": 0.5,
  "warp": 0.08925,
  "gamma": 1,
  "warp_speed": 0.626,
  "wave_scale": 1.157,
  "decay": 1
}