{
  "name": "Idiot24-7-gohtsthirdeye",
  "init_code": "",
  "per_frame": "ib_g\nib_r\nib_b\nib_size\nwave_b",
  "per_pixel": "rot",
  "shapes": [],
  "waves": [
    {
      "enabled": 1,
      "samples": 512,
      "spectrum": 0,
      "dots": 0,
      "thick": 0,
      "additive": 0,
      "r": 1,
      "g": 1,
      "b": 1,
      "a": 1,
      "scaling": 1,
      "smoothing": 0.5,
      "sep": 0,
      "code_per_frame": "",
      "code_per_point": ""
    }
  ],
  "zoom": 0.989618,
  "rot": -1,
  "cx": 0.5,
  "cy": 0.5,
  "warp": 0.01,
  "gamma": 1,
  "warp_speed": 1,
  "wave_scale": 0.05325,
  "decay": 1
}