{
  "name": "suksma - trial by pumpbot - log smell2",
  "init_code": "initq30",
  "per_frame": "warp\nbass_on\ntreb_on\nstate\nwave_r\nwave_g\nwave_b\nob_r\nob_g\nob_b\nob_size\nbass_effect\ntreb_effect\nnet_effect\nzoom\nwave_size\nq1\nrunbass\nruntreb\nrunmid\nq30\nmonitor\nq20",
  "per_pixel": "rot\nzoom\ndx",
  "shapes": [
    {
      "enabled": 0,
      "sides": 4,
      "additive": 0,
      "thickOutline": 0,
      "textured": 0,
      "code": "",
      "baseVals": {
        "x": 0.5,
        "y": 0.5,
        "ang": 0,
        "size": 0.1,
        "r": 1,
        "g": 0,
        "b": 0,
        "a": 1,
        "r2": 0,
        "g2": 1,
        "b2": 0,
        "a2": 0,
        "border_r": 1,
        "border_g": 1,
        "border_b": 1,
        "border_a": 0.1,
        "tex_ang": 0,
        "tex_zoom": 1
      }
    },
    {
      "enabled": 0,
      "sides": 4,
      "additive": 0,
      "thickOutline": 0,
      "textured": 0,
      "code": "",
      "baseVals": {
        "x": 0.5,
        "y": 0.5,
        "ang": 0,
        "size": 0.1,
        "r": 1,
        "g": 0,
        "b": 0,
        "a": 1,
        "r2": 0,
        "g2": 1,
        "b2": 0,
        "a2": 0,
        "border_r": 1,
        "border_g": 1,
        "border_b": 1,
        "border_a": 0.1,
        "tex_ang": 0,
        "tex_zoom": 1
      }
    },
    {
      "enabled": 0,
      "sides": 4,
      "additive": 0,
      "thickOutline": 0,
      "textured": 0,
      "code": "",
      "baseVals": {
        "x": 0.5,
        "y": 0.5,
        "ang": 0,
        "size": 0.1,
        "r": 1,
        "g": 0,
        "b": 0,
        "a": 1,
        "r2": 0,
        "g2": 1,
        "b2": 0,
        "a2": 0,
        "border_r": 1,
        "border_g": 1,
        "border_b": 1,
        "border_a": 0.1,
        "tex_ang": 0,
        "tex_zoom": 1
      }
    },
    {
      "enabled": 0,
      "sides": 4,
      "additive": 0,
      "thickOutline": 0,
      "textured": 0,
      "code": "",
      "baseVals": {
        "x": 0.5,
        "y": 0.5,
        "ang": 0,
        "size": 0.1,
        "r": 1,
        "g": 0,
        "b": 0,
        "a": 1,
        "r2": 0,
        "g2": 1,
        "b2": 0,
        "a2": 0,
        "border_r": 1,
        "border_g": 1,
        "border_b": 1,
        "border_a": 0.1,
        "tex_ang": 0,
        "tex_zoom": 1
      }
    }
  ],
  "waves": [
    {
      "enabled": 0,
      "samples": 512,
      "spectrum": 0,
      "dots": 0,
      "thick": 0,
      "additive": 0,
      "r": 1,
      "g": 1,
      "b": 1,
      "a": 1,
      "scaling": 1,
      "smoothing": 0.5,
      "sep": 0,
      "code_per_frame": "",
      "code_per_point": "x\ny\nr\ng\nb"
    },
    {
      "enabled": 0,
      "samples": 512,
      "spectrum": 0,
      "dots": 0,
      "thick": 0,
      "additive": 0,
      "r": 1,
      "g": 1,
      "b": 1,
      "a": 1,
      "scaling": 1,
      "smoothing": 0.5,
      "sep": 0,
      "code_per_frame": "",
      "code_per_point": "x\ny\nr\ng\nb"
    },
    {
      "enabled": 0,
      "samples": 512,
      "spectrum": 0,
      "dots": 0,
      "thick": 0,
      "additive": 0,
      "r": 1,
      "g": 1,
      "b": 1,
      "a": 1,
      "scaling": 1,
      "smoothing": 0.5,
      "sep": 0,
      "code_per_frame": "",
      "code_per_point": "x\ny\nr\ng\nb"
    },
    {
      "enabled": 1,
      "samples": 512,
      "spectrum": 1,
      "dots": 0,
      "thick": 1,
      "additive": 1,
      "r": 1,
      "g": 1,
      "b": 1,
      "a": 0.5,
      "scaling": 1,
      "smoothing": 0.5,
      "sep": 256,
      "code_per_frame": "",
      "code_per_point": "x\ny\nr\ng\nb"
    }
  ],
  "zoom": 1,
  "rot": 0.02,
  "cx": 0.56,
  "cy": 0.5,
  "warp": 1,
  "gamma": 2.001,
  "warp_speed": 1,
  "wave_scale": 1,
  "decay": 0.9
}